{
  "type": "minecraft:block",
  "pools": [
    {
      "rolls": 1,
      "conditions": [
        { "condition": "minecraft:survives_explosion" }
      ],
      "entries": [
        {
          "type": "minecraft:item",
          "name": "idos_first_mod:bong",
          "conditions": [
            {
              "condition": "minecraft:match_tool",
              "predicate": {
                "enchantments": [
                  {
                    "enchantment": "minecraft:silk_touch",
                    "levels": { "min": 1 }
                  }
                ]
              }
            }
          ]
        }
      ]
    }
  ]
}
